outcome/devkit_api/__init__.py
outcome/devkit_api/assertions.py
outcome/devkit_api/fixtures/__init__.py
outcome/devkit_api/fixtures/app.py
outcome/devkit_api/fixtures/config.py
outcome/devkit_api/fixtures/keys/incorrect.public.key
outcome/devkit_api/fixtures/keys/private.key
outcome/devkit_api/fixtures/keys/public.key
outcome/devkit_api/fixtures/keys.py
outcome/devkit_api/pact/__init__.py
outcome/devkit_api/pact/pactman/__init__.py
outcome/devkit_api/pact/pactman/mock/__init__.py
outcome/devkit_api/pact/pactman/mock/mock_urlopen.py
outcome/devkit_api/pact/pactman/mock/pact.py
outcome/devkit_api/py.typed
outcome/devkit_api/testclient.py
outcome/devkit_api/tools.py
outcome_devkit_api-0.3.1.dist-info/WHEEL
outcome_devkit_api-0.3.1.dist-info/METADATA
outcome_devkit_api-0.3.1.dist-info/RECORD
